string2dict/__init__.py
string2dict/old_string2dict.py
string2dict/string2dict.py
string2dict-0.0.9.dist-info/METADATA
string2dict-0.0.9.dist-info/WHEEL
string2dict-0.0.9.dist-info/top_level.txt
string2dict-0.0.9.dist-info/RECORD
